pytest_snowflake_bdd/__init__.py
pytest_snowflake_bdd/plugin.py
pytest_snowflake_bdd/utils.py
pytest_snowflake_bdd-0.2.2.dist-info/LICENSE
pytest_snowflake_bdd-0.2.2.dist-info/METADATA
pytest_snowflake_bdd-0.2.2.dist-info/WHEEL
pytest_snowflake_bdd-0.2.2.dist-info/entry_points.txt
pytest_snowflake_bdd-0.2.2.dist-info/top_level.txt
pytest_snowflake_bdd-0.2.2.dist-info/RECORD
