Metadata-Version: 2.1
Name: pytest-snowflake-bdd
Version: 0.2.2
Summary: Setup test data and run tests on snowflake in BDD style!
Home-page: https://github.com/tilakpatidar/pytest-snowflake_bdd
Author: Tilak Patidar
Author-email: tilakpatidar@gmail.com
Maintainer: Tilak Patidar
Maintainer-email: tilakpatidar@gmail.com
License: MIT
Platform: UNKNOWN
Classifier: Development Status :: 4 - Beta
Classifier: Framework :: Pytest
Classifier: Intended Audience :: Developers
Classifier: Topic :: Software Development :: Testing
Classifier: Topic :: Database
Classifier: Topic :: Software Development :: Testing :: BDD
Classifier: Programming Language :: Python
Classifier: Programming Language :: Python :: 3.6
Classifier: Programming Language :: Python :: 3.7
Classifier: Programming Language :: Python :: 3.8
Classifier: Programming Language :: Python :: 3.9
Classifier: Programming Language :: Python :: Implementation :: CPython
Classifier: Programming Language :: Python :: Implementation :: PyPy
Classifier: Framework :: Pytest
Classifier: Operating System :: OS Independent
Classifier: License :: OSI Approved :: MIT License
Requires-Python: >=3.6.7
License-File: LICENSE
Requires-Dist: pytest (>=6.2.0)
Requires-Dist: pytest-bdd (>=3.2.1)
Requires-Dist: snowflake-sqlalchemy (>=1.3.2)
Requires-Dist: SQLAlchemy (>=1.4.27)
Requires-Dist: pandas (>=0.25.3)
Requires-Dist: python-dateutil (>=2.8.2)
